geoprobe/_2dHeader.py
geoprobe/__init__.py
geoprobe/_volHeader.py
geoprobe/colormap.py
geoprobe/common.py
geoprobe/data2d.py
geoprobe/ezfault.py
geoprobe/horizon.py
geoprobe/swfault.py
geoprobe/tsurf.py
geoprobe/utilities.py
geoprobe/volume.py
geoprobe/well.py
geoprobe-0.3.1.dist-info/DESCRIPTION.rst
geoprobe-0.3.1.dist-info/METADATA
geoprobe-0.3.1.dist-info/RECORD
geoprobe-0.3.1.dist-info/WHEEL
geoprobe-0.3.1.dist-info/metadata.json
geoprobe-0.3.1.dist-info/top_level.txt
