Metadata-Version: 2.0
Name: geoprobe
Version: 0.3.1
Summary: Reads and (partially) writes seismic data in Landmark's Geoprobe format
Home-page: https://github.com/joferkington/python-geoprobe
Author: Joe Kington
Author-email: joferkington@gmail.com
License: MIT
Platform: UNKNOWN
